[
  {
    "id": "9lBhxGDXH8NfTfwC2gQu",
    "locationId": "FgaFLGYrbGZSBVprTkhR",
    "contactName": "(220) 356-9790",
    "firstName": null,
    "lastName": null,
    "firstNameRaw": null,
    "lastNameRaw": null,
    "companyName": null,
    "email": "[REDACTED:EMAIL]",
    "phone": "[REDACTED:PHONE]",
    "dnd": false,
    "dndSettings": {},
    "type": "lead",
    "source": null,
    "assignedTo": null,
    "city": null,
    "state": "OH",
    "postalCode": null,
    "address1": null,
    "dateAdded": "2026-01-23T19:20:52.537Z",
    "dateUpdated": "2026-01-23T19:20:52.537Z",
    "dateOfBirth": null,
    "businessId": null,
    "tags": [
      "couldn't find caller name"
    ],
    "followers": [],
    "country": "US",
    "website": null,
    "timezone": null,
    "profilePhoto": null,
    "additionalEmails": [],
    "attributions": [
      {
        "utmSessionSource": "Other",
        "medium": "other",
        "isFirst": true
      }
    ],
    "customFields": []
  },
  {
    "id": "OOXVwjrLUBhRfQCwxM1B",
    "locationId": "FgaFLGYrbGZSBVprTkhR",
    "contactName": "mahesh s.",
    "firstName": "mahesh",
    "lastName": "s.",
    "firstNameRaw": "Mahesh",
    "lastNameRaw": "S.",
    "companyName": null,
    "email": "[REDACTED:EMAIL]",
    "phone": "[REDACTED:PHONE]",
    "dnd": false,
    "type": "lead",
    "source": "Google Sheets - RB2B Import",
    "assignedTo": "LBHzbBcLa6EFBkh7VNxu",
    "city": "Raleigh",
    "state": "NC",
    "postalCode": null,
    "address1": null,
    "dateAdded": "2026-01-23T18:34:18.857Z",
    "dateUpdated": "2026-01-23T18:37:57.511Z",
    "dateOfBirth": null,
    "businessId": null,
    "tags": [
      "low",
      "rb2b-enriched",
      "email_corporate",
      "ai ownership - active sequence"
    ],
    "followers": [],
    "country": "US",
    "website": "https://plc.pearson.com/",
    "timezone": null,
    "profilePhoto": null,
    "additionalEmails": [],
    "dndSettings": {},
    "customFields": []
  },
  {
    "id": "hj1zrYNr3K4SAy2DQLjD",
    "locationId": "FgaFLGYrbGZSBVprTkhR",
    "contactName": "cynthia",
    "firstName": "cynthia",
    "lastName": null,
    "firstNameRaw": "Cynthia",
    "lastNameRaw": null,
    "companyName": null,
    "email": "[REDACTED:EMAIL]",
    "phone": "[REDACTED:PHONE]",
    "dnd": false,
    "dndSettings": {},
    "type": "lead",
    "source": null,
    "assignedTo": "LBHzbBcLa6EFBkh7VNxu",
    "city": null,
    "state": null,
    "postalCode": null,
    "address1": null,
    "dateAdded": "2026-01-23T18:21:29.755Z",
    "dateUpdated": "2026-01-23T20:07:27.363Z",
    "dateOfBirth": null,
    "businessId": null,
    "tags": [
      "#vistage_al_jan23_2026"
    ],
    "followers": [],
    "country": "US",
    "website": null,
    "timezone": null,
    "profilePhoto": null,
    "additionalEmails": [],
    "attributions": [
      {
        "utmSessionSource": "Other",
        "isFirst": true,
        "medium": "conversation"
      }
    ],
    "customFields": []
  },
  {
    "id": "cpBjwul20byvE3iVGXVE",
    "locationId": "FgaFLGYrbGZSBVprTkhR",
    "contactName": "bahram",
    "firstName": "bahram",
    "lastName": null,
    "firstNameRaw": "Bahram",
    "lastNameRaw": null,
    "companyName": null,
    "email": "[REDACTED:EMAIL]",
    "phone": "[REDACTED:PHONE]",
    "dnd": false,
    "dndSettings": {},
    "type": "lead",
    "source": null,
    "assignedTo": "LBHzbBcLa6EFBkh7VNxu",
    "city": null,
    "state": null,
    "postalCode": null,
    "address1": null,
    "dateAdded": "2026-01-23T18:20:56.709Z",
    "dateUpdated": "2026-01-23T20:06:49.238Z",
    "dateOfBirth": null,
    "businessId": null,
    "tags": [
      "#vistage_al_jan23_2026"
    ],
    "followers": [],
    "country": "US",
    "website": null,
    "timezone": null,
    "profilePhoto": null,
    "additionalEmails": [],
    "attributions": [
      {
        "utmSessionSource": "Other",
        "isFirst": true,
        "medium": "conversation"
      }
    ],
    "customFields": []
  },
  {
    "id": "7Y271ptktYpQg6pwjTHJ",
    "locationId": "FgaFLGYrbGZSBVprTkhR",
    "contactName": "(714) 944-5257",
    "firstName": null,
    "lastName": null,
    "firstNameRaw": null,
    "lastNameRaw": null,
    "companyName": null,
    "email": "[REDACTED:EMAIL]",
    "phone": "[REDACTED:PHONE]",
    "dnd": false,
    "dndSettings": {},
    "type": "lead",
    "source": null,
    "assignedTo": "LBHzbBcLa6EFBkh7VNxu",
    "city": null,
    "state": null,
    "postalCode": null,
    "address1": null,
    "dateAdded": "2026-01-23T18:20:56.090Z",
    "dateUpdated": "2026-01-23T20:08:08.647Z",
    "dateOfBirth": null,
    "businessId": null,
    "tags": [
      "#vistage_al_jan23_2026"
    ],
    "followers": [],
    "country": "US",
    "website": null,
    "timezone": null,
    "profilePhoto": null,
    "additionalEmails": [],
    "attributions": [
      {
        "utmSessionSource": "Other",
        "isFirst": true,
        "medium": "conversation"
      }
    ],
    "customFields": []
  },
  {
    "id": "ec5kvgxuIIiQqKAGLACe",
    "locationId": "FgaFLGYrbGZSBVprTkhR",
    "contactName": "(510) 459-7131",
    "firstName": null,
    "lastName": null,
    "firstNameRaw": null,
    "lastNameRaw": null,
    "companyName": null,
    "email": "[REDACTED:EMAIL]",
    "phone": "[REDACTED:PHONE]",
    "dnd": false,
    "dndSettings": {},
    "type": "lead",
    "source": null,
    "assignedTo": "LBHzbBcLa6EFBkh7VNxu",
    "city": null,
    "state": null,
    "postalCode": null,
    "address1": null,
    "dateAdded": "2026-01-23T18:20:54.358Z",
    "dateUpdated": "2026-01-23T20:08:49.981Z",
    "dateOfBirth": null,
    "businessId": null,
    "tags": [
      "#vistage_al_jan23_2026"
    ],
    "followers": [],
    "country": "US",
    "website": null,
    "timezone": null,
    "profilePhoto": null,
    "additionalEmails": [],
    "attributions": [
      {
        "utmSessionSource": "Other",
        "isFirst": true,
        "medium": "conversation"
      }
    ],
    "customFields": []
  },
  {
    "id": "TY1mVI8DBJAxJueCBQG8",
    "locationId": "FgaFLGYrbGZSBVprTkhR",
    "contactName": "(949) 943-7711",
    "firstName": null,
    "lastName": null,
    "firstNameRaw": null,
    "lastNameRaw": null,
    "companyName": null,
    "email": "[REDACTED:EMAIL]",
    "phone": "[REDACTED:PHONE]",
    "dnd": false,
    "dndSettings": {},
    "type": "lead",
    "source": null,
    "assignedTo": "LBHzbBcLa6EFBkh7VNxu",
    "city": null,
    "state": null,
    "postalCode": null,
    "address1": null,
    "dateAdded": "2026-01-23T18:20:45.091Z",
    "dateUpdated": "2026-01-23T20:09:42.628Z",
    "dateOfBirth": null,
    "businessId": null,
    "tags": [
      "#vistage_al_jan23_2026"
    ],
    "followers": [],
    "country": "US",
    "website": null,
    "timezone": null,
    "profilePhoto": null,
    "additionalEmails": [],
    "attributions": [
      {
        "utmSessionSource": "Other",
        "isFirst": true,
        "medium": "conversation"
      }
    ],
    "customFields": []
  },
  {
    "id": "7GvigGi1SvSCfXArzZy1",
    "locationId": "FgaFLGYrbGZSBVprTkhR",
    "contactName": "(716) 393-0112",
    "firstName": null,
    "lastName": null,
    "firstNameRaw": null,
    "lastNameRaw": null,
    "companyName": null,
    "email": "[REDACTED:EMAIL]",
    "phone": "[REDACTED:PHONE]",
    "dnd": false,
    "dndSettings": {},
    "type": "lead",
    "source": null,
    "assignedTo": "LBHzbBcLa6EFBkh7VNxu",
    "city": null,
    "state": null,
    "postalCode": null,
    "address1": null,
    "dateAdded": "2026-01-23T18:20:42.913Z",
    "dateUpdated": "2026-01-23T20:10:01.365Z",
    "dateOfBirth": null,
    "businessId": null,
    "tags": [
      "#vistage_al_jan23_2026"
    ],
    "followers": [],
    "country": "US",
    "website": null,
    "timezone": null,
    "profilePhoto": null,
    "additionalEmails": [],
    "attributions": [
      {
        "utmSessionSource": "Other",
        "isFirst": true,
        "medium": "conversation"
      }
    ],
    "customFields": []
  },
  {
    "id": "KplEPr9kJpagPu1Jm88P",
    "locationId": "FgaFLGYrbGZSBVprTkhR",
    "contactName": "(714) 606-4579",
    "firstName": null,
    "lastName": null,
    "firstNameRaw": null,
    "lastNameRaw": null,
    "companyName": null,
    "email": "[REDACTED:EMAIL]",
    "phone": "[REDACTED:PHONE]",
    "dnd": false,
    "dndSettings": {},
    "type": "lead",
    "source": null,
    "assignedTo": "LBHzbBcLa6EFBkh7VNxu",
    "city": null,
    "state": null,
    "postalCode": null,
    "address1": null,
    "dateAdded": "2026-01-23T18:20:42.416Z",
    "dateUpdated": "2026-01-23T20:09:24.038Z",
    "dateOfBirth": null,
    "businessId": null,
    "tags": [
      "#vistage_al_jan23_2026"
    ],
    "followers": [],
    "country": "US",
    "website": null,
    "timezone": null,
    "profilePhoto": null,
    "additionalEmails": [],
    "attributions": [
      {
        "utmSessionSource": "Other",
        "isFirst": true,
        "medium": "conversation"
      }
    ],
    "customFields": []
  },
  {
    "id": "kb2p1otdw1fcLNQfUejY",
    "locationId": "FgaFLGYrbGZSBVprTkhR",
    "contactName": "(657) 757-6521",
    "firstName": null,
    "lastName": null,
    "firstNameRaw": null,
    "lastNameRaw": null,
    "companyName": null,
    "email": "[REDACTED:EMAIL]",
    "phone": "[REDACTED:PHONE]",
    "dnd": false,
    "dndSettings": {},
    "type": "lead",
    "source": null,
    "assignedTo": "LBHzbBcLa6EFBkh7VNxu",
    "city": null,
    "state": null,
    "postalCode": null,
    "address1": null,
    "dateAdded": "2026-01-23T18:20:41.384Z",
    "dateUpdated": "2026-01-23T19:00:21.029Z",
    "dateOfBirth": null,
    "businessId": null,
    "tags": [
      "#vistage_al_jan23_2026"
    ],
    "followers": [],
    "country": "US",
    "website": null,
    "timezone": null,
    "profilePhoto": null,
    "additionalEmails": [],
    "attributions": [
      {
        "utmSessionSource": "Other",
        "isFirst": true,
        "medium": "conversation"
      }
    ],
    "customFields": []
  },
  {
    "id": "mKt1hIkdtT0IbFIfnDJ5",
    "locationId": "FgaFLGYrbGZSBVprTkhR",
    "contactName": "(805) 660-5560",
    "firstName": null,
    "lastName": null,
    "firstNameRaw": null,
    "lastNameRaw": null,
    "companyName": null,
    "email": "[REDACTED:EMAIL]",
    "phone": "[REDACTED:PHONE]",
    "dnd": false,
    "dndSettings": {},
    "type": "lead",
    "source": null,
    "assignedTo": "LBHzbBcLa6EFBkh7VNxu",
    "city": null,
    "state": null,
    "postalCode": null,
    "address1": null,
    "dateAdded": "2026-01-23T18:20:41.223Z",
    "dateUpdated": "2026-01-23T19:00:02.946Z",
    "dateOfBirth": null,
    "businessId": null,
    "tags": [
      "#vistage_al_jan23_2026"
    ],
    "followers": [],
    "country": "US",
    "website": null,
    "timezone": null,
    "profilePhoto": null,
    "additionalEmails": [],
    "attributions": [
      {
        "utmSessionSource": "Other",
        "isFirst": true,
        "medium": "conversation"
      }
    ],
    "customFields": []
  },
  {
    "id": "ottiMbhYO2eO7xmQpq9K",
    "locationId": "FgaFLGYrbGZSBVprTkhR",
    "contactName": "(562) 508-8410",
    "firstName": null,
    "lastName": null,
    "firstNameRaw": null,
    "lastNameRaw": null,
    "companyName": null,
    "email": "[REDACTED:EMAIL]",
    "phone": "[REDACTED:PHONE]",
    "dnd": false,
    "dndSettings": {},
    "type": "lead",
    "source": null,
    "assignedTo": "LBHzbBcLa6EFBkh7VNxu",
    "city": null,
    "state": null,
    "postalCode": null,
    "address1": null,
    "dateAdded": "2026-01-23T18:20:39.968Z",
    "dateUpdated": "2026-01-23T18:59:15.913Z",
    "dateOfBirth": null,
    "businessId": null,
    "tags": [
      "#vistage_al_jan23_2026"
    ],
    "followers": [],
    "country": "US",
    "website": null,
    "timezone": null,
    "profilePhoto": null,
    "additionalEmails": [],
    "attributions": [
      {
        "utmSessionSource": "Other",
        "isFirst": true,
        "medium": "conversation"
      }
    ],
    "customFields": []
  },
  {
    "id": "ezUaHSB2bMRdmlcSgAWp",
    "locationId": "FgaFLGYrbGZSBVprTkhR",
    "contactName": "(714) 619-1995",
    "firstName": null,
    "lastName": null,
    "firstNameRaw": null,
    "lastNameRaw": null,
    "companyName": null,
    "email": "[REDACTED:EMAIL]",
    "phone": "[REDACTED:PHONE]",
    "dnd": false,
    "dndSettings": {},
    "type": "lead",
    "source": null,
    "assignedTo": "LBHzbBcLa6EFBkh7VNxu",
    "city": null,
    "state": null,
    "postalCode": null,
    "address1": null,
    "dateAdded": "2026-01-23T18:20:37.642Z",
    "dateUpdated": "2026-01-23T18:58:52.074Z",
    "dateOfBirth": null,
    "businessId": null,
    "tags": [
      "#vistage_al_jan23_2026"
    ],
    "followers": [],
    "country": "US",
    "website": null,
    "timezone": null,
    "profilePhoto": null,
    "additionalEmails": [],
    "attributions": [
      {
        "utmSessionSource": "Other",
        "isFirst": true,
        "medium": "conversation"
      }
    ],
    "customFields": []
  },
  {
    "id": "1yzEPAxhUbz8lUuX2G8m",
    "locationId": "FgaFLGYrbGZSBVprTkhR",
    "contactName": "(562) 682-6018",
    "firstName": null,
    "lastName": null,
    "firstNameRaw": null,
    "lastNameRaw": null,
    "companyName": null,
    "email": "[REDACTED:EMAIL]",
    "phone": "[REDACTED:PHONE]",
    "dnd": false,
    "dndSettings": {},
    "type": "lead",
    "source": null,
    "assignedTo": "LBHzbBcLa6EFBkh7VNxu",
    "city": null,
    "state": null,
    "postalCode": null,
    "address1": null,
    "dateAdded": "2026-01-23T18:20:35.248Z",
    "dateUpdated": "2026-01-23T18:59:40.967Z",
    "dateOfBirth": null,
    "businessId": null,
    "tags": [
      "#vistage_al_jan23_2026"
    ],
    "followers": [],
    "country": "US",
    "website": null,
    "timezone": null,
    "profilePhoto": null,
    "additionalEmails": [],
    "attributions": [
      {
        "utmSessionSource": "Other",
        "isFirst": true,
        "medium": "conversation"
      }
    ],
    "customFields": []
  },
  {
    "id": "V38lun0RDbtphb7y2L7y",
    "locationId": "FgaFLGYrbGZSBVprTkhR",
    "contactName": "mary ellen",
    "firstName": "mary",
    "lastName": "ellen",
    "firstNameRaw": "Mary",
    "lastNameRaw": "Ellen",
    "companyName": null,
    "email": "[REDACTED:EMAIL]",
    "phone": "[REDACTED:PHONE]",
    "dnd": false,
    "dndSettings": {},
    "type": "lead",
    "source": "Google Sheets - RB2B Import",
    "assignedTo": "ExNmJ3Pn0mprYDpgWq1y",
    "city": "Brooklyn",
    "state": "NY",
    "postalCode": null,
    "address1": null,
    "dateAdded": "2026-01-23T16:50:20.138Z",
    "dateUpdated": "2026-01-23T16:54:26.810Z",
    "dateOfBirth": null,
    "businessId": null,
    "tags": [
      "medium",
      "rb2b-enriched",
      "email_corporate",
      "ai ownership - active sequence"
    ],
    "followers": [],
    "country": "US",
    "website": null,
    "timezone": null,
    "profilePhoto": null,
    "additionalEmails": [],
    "customFields": []
  },
  {
    "id": "yWIVq4S6aJVa8tHCMm3y",
    "locationId": "FgaFLGYrbGZSBVprTkhR",
    "contactName": "melissa whatley",
    "firstName": "melissa",
    "lastName": "whatley",
    "firstNameRaw": "Melissa",
    "lastNameRaw": "Whatley",
    "companyName": null,
    "email": "[REDACTED:EMAIL]",
    "phone": "[REDACTED:PHONE]",
    "dnd": false,
    "dndSettings": {},
    "type": "lead",
    "source": "Google Sheets - RB2B Import",
    "assignedTo": "LBHzbBcLa6EFBkh7VNxu",
    "city": "McAllen",
    "state": "TX",
    "postalCode": null,
    "address1": null,
    "dateAdded": "2026-01-23T16:45:20.098Z",
    "dateUpdated": "2026-01-23T16:49:10.813Z",
    "dateOfBirth": null,
    "businessId": null,
    "tags": [
      "medium",
      "rb2b-enriched",
      "email_corporate",
      "ai ownership - active sequence"
    ],
    "followers": [],
    "country": "US",
    "website": "http://ucsc.edu",
    "timezone": null,
    "profilePhoto": null,
    "additionalEmails": [],
    "customFields": []
  },
  {
    "id": "1jPSOzD5Dmmy2QTGYrzm",
    "locationId": "FgaFLGYrbGZSBVprTkhR",
    "contactName": "justin mcgowan",
    "firstName": "justin",
    "lastName": "mcgowan",
    "firstNameRaw": "Justin",
    "lastNameRaw": "McGowan",
    "companyName": null,
    "email": "[REDACTED:EMAIL]",
    "phone": "[REDACTED:PHONE]",
    "dnd": false,
    "dndSettings": {},
    "type": "lead",
    "source": null,
    "assignedTo": "ExNmJ3Pn0mprYDpgWq1y",
    "city": null,
    "state": null,
    "postalCode": null,
    "address1": null,
    "dateAdded": "2026-01-23T16:25:23.434Z",
    "dateUpdated": "2026-01-23T16:28:49.097Z",
    "dateOfBirth": null,
    "businessId": null,
    "tags": [
      "email_corporate",
      "ai ownership - active sequence"
    ],
    "followers": [],
    "country": "US",
    "website": null,
    "timezone": null,
    "profilePhoto": null,
    "additionalEmails": [],
    "attributions": [
      {
        "utmSessionSource": "CRM UI",
        "isFirst": true,
        "medium": "manual"
      }
    ],
    "customFields": []
  },
  {
    "id": "MESBie8efsYQqL0Kn8Zt",
    "locationId": "FgaFLGYrbGZSBVprTkhR",
    "contactName": "donald chapelle",
    "firstName": "donald",
    "lastName": "chapelle",
    "firstNameRaw": "Donald",
    "lastNameRaw": "Chapelle",
    "companyName": null,
    "email": "[REDACTED:EMAIL]",
    "phone": "[REDACTED:PHONE]",
    "dnd": false,
    "dndSettings": {
      "SMS": {
        "message": "STOP_KEYWORD",
        "status": "permanent"
      }
    },
    "type": "lead",
    "source": "Google Sheets - RB2B Import",
    "assignedTo": "ExNmJ3Pn0mprYDpgWq1y",
    "city": "Boston",
    "state": "MA",
    "postalCode": null,
    "address1": null,
    "dateAdded": "2026-01-23T16:07:21.411Z",
    "dateUpdated": "2026-01-23T16:10:31.393Z",
    "dateOfBirth": null,
    "businessId": null,
    "tags": [
      "high",
      "rb2b-enriched",
      "email_corporate",
      "ai ownership - active sequence"
    ],
    "followers": [],
    "country": "US",
    "website": "https://brillianticesculpture.com",
    "timezone": null,
    "profilePhoto": null,
    "additionalEmails": [],
    "customFields": []
  },
  {
    "id": "MwkHWxRput3h5GN1V5xc",
    "locationId": "FgaFLGYrbGZSBVprTkhR",
    "contactName": "hina popal",
    "firstName": "hina",
    "lastName": "popal",
    "firstNameRaw": "Hina",
    "lastNameRaw": "Popal",
    "companyName": null,
    "email": "[REDACTED:EMAIL]",
    "phone": "[REDACTED:PHONE]",
    "dnd": false,
    "type": "lead",
    "source": "Google Sheets - RB2B Import",
    "assignedTo": "ExNmJ3Pn0mprYDpgWq1y",
    "city": "Ashburn",
    "state": "VA",
    "postalCode": null,
    "address1": null,
    "dateAdded": "2026-01-23T14:32:21.029Z",
    "dateUpdated": "2026-01-23T14:45:17.848Z",
    "dateOfBirth": null,
    "businessId": null,
    "tags": [
      "high",
      "rb2b-enriched",
      "email_corporate",
      "ai ownership - active sequence"
    ],
    "followers": [],
    "country": "US",
    "website": "https://www.digitalocean.com",
    "timezone": null,
    "profilePhoto": null,
    "additionalEmails": [],
    "dndSettings": {},
    "customFields": []
  },
  {
    "id": "kgtdThtdexpLBEy8yJCJ",
    "locationId": "FgaFLGYrbGZSBVprTkhR",
    "contactName": "nitesh jain",
    "firstName": "nitesh",
    "lastName": "jain",
    "firstNameRaw": "Nitesh",
    "lastNameRaw": "Jain",
    "companyName": null,
    "email": "[REDACTED:EMAIL]",
    "phone": "[REDACTED:PHONE]",
    "dnd": false,
    "dndSettings": {},
    "type": "lead",
    "source": "Google Sheets - RB2B Import",
    "assignedTo": "ExNmJ3Pn0mprYDpgWq1y",
    "city": "Piscataway",
    "state": "NJ",
    "postalCode": null,
    "address1": null,
    "dateAdded": "2026-01-23T14:10:21.802Z",
    "dateUpdated": "2026-01-23T14:22:37.963Z",
    "dateOfBirth": null,
    "businessId": null,
    "tags": [
      "high",
      "rb2b-enriched",
      "email_consumer"
    ],
    "followers": [],
    "country": "US",
    "website": "https://www.c5i.ai/",
    "timezone": null,
    "profilePhoto": null,
    "additionalEmails": [],
    "customFields": []
  }
]